Metadata-Version: 2.4
Name: llm-tools-simpleeval
Version: 0.1.1
Summary: Make simple_eval available as an LLM tool
Author: Simon Willison
License-Expression: Apache-2.0
Project-URL: Homepage, https://github.com/simonw/llm-tools-simpleeval
Project-URL: Changelog, https://github.com/simonw/llm-tools-simpleeval/releases
Project-URL: Issues, https://github.com/simonw/llm-tools-simpleeval/issues
Project-URL: CI, https://github.com/simonw/llm-tools-simpleeval/actions
Requires-Python: >=3.9
License-File: LICENSE
Requires-Dist: llm
Requires-Dist: simpleeval
Provides-Extra: test
Requires-Dist: pytest; extra == "test"
Dynamic: license-file
